sarxarray/__init__.py
sarxarray/_io.py
sarxarray/conf.py
sarxarray/stack.py
sarxarray/utils.py
sarxarray-1.2.3.dist-info/licenses/LICENSE
sarxarray-1.2.3.dist-info/METADATA
sarxarray-1.2.3.dist-info/WHEEL
sarxarray-1.2.3.dist-info/top_level.txt
sarxarray-1.2.3.dist-info/RECORD
