Metadata-Version: 2.4
Name: sarxarray
Version: 1.2.3
Summary: Xarray extension for Synthetic Aperture Radar (SAR) data
Author: Fakhereh Sarah Alidoost, Simon van Diepen, Pranav Chandramouli, Francesco Nattino, Freek van Leijen
Author-email: Ou Ku <o.ku@esciencecenter.nl>
License:                                  Apache License
Project-URL: repository, https://github.com/TUDelftGeodesy/sarxarray
Project-URL: doi, https://doi.org/10.5281/zenodo.7717112
Project-URL: documentation, https://tudelftgeodesy.github.io/sarxarray/
Project-URL: changelog, https://tudelftgeodesy.github.io/sarxarray/CHANGELOG/
Keywords: radar,sar,insar,earth observation,distributed computing
Classifier: Development Status :: 3 - Alpha
Classifier: Intended Audience :: Developers
Classifier: License :: OSI Approved :: Apache Software License
Classifier: Natural Language :: English
Classifier: Programming Language :: Python :: 3.10
Classifier: Programming Language :: Python :: 3.11
Classifier: Programming Language :: Python :: 3.12
Requires-Python: >=3.10
License-File: LICENSE
Requires-Dist: dask[complete]
Requires-Dist: xarray
Requires-Dist: numpy
Requires-Dist: distributed
Requires-Dist: zarr
Provides-Extra: dev
Requires-Dist: pytest; extra == "dev"
Requires-Dist: pytest-cov; extra == "dev"
Requires-Dist: pycodestyle; extra == "dev"
Requires-Dist: ruff; extra == "dev"
Requires-Dist: pre-commit; extra == "dev"
Provides-Extra: docs
Requires-Dist: mkdocs; extra == "docs"
Requires-Dist: mkdocs-material; extra == "docs"
Requires-Dist: mkdocs-jupyter; extra == "docs"
Requires-Dist: mkdocstrings[python]; extra == "docs"
Requires-Dist: mkdocs-gen-files; extra == "docs"
Provides-Extra: demo
Requires-Dist: jupyterlab; extra == "demo"
Requires-Dist: matplotlib; extra == "demo"
Dynamic: license-file
